Workbook

Sheet Assumptions
C1: In Crores
A2: Label | B2: Forecast Value | C2: Explanation
A3: Revenue growth rate | B3: 0.12
A4: Raw Material Cost % of Sales | B4: =AVERAGE('Income Statement'!D6,'Income Statement'!E6,'Income Statement'!F6) -> 0.88487 | C4: avg of last 3 yrs
A5: Employee Cost % of Sales | B5: =AVERAGE('Income Statement'!D14,'Income Statement'!E14,'Income Statement'!F14) -> 0.034411696 | C5: avg of last 3 yrs
A6: Selling & Admin % of Sales | B6: =AVERAGE('Income Statement'!D16,'Income Statement'!E16,'Income Statement'!F16) -> 0.056392642 | C6: avg of last 3 yrs
A7: Other Expenses % of Sales | B7: =AVERAGE('Income Statement'!D18,'Income Statement'!E18,'Income Statement'!F18) -> 0.018611715 | C7: avg of last 3 yrs
A8: Depreciation % of Sales | B8: =AVERAGE('Income Statement'!D20,'Income Statement'!E20,'Income Statement'!F20) -> 0.010775326 | C8: avg of last 3 yrs
A9: Power & fuel % of sales | B9: =AVERAGE('Income Statement'!D10,'Income Statement'!E10,'Income Statement'!F10) -> 0.0012244648 | C9: avg of last 3 yrs
A10: Other mfr exp % of sales | B10: =AVERAGE('Income Statement'!D12,'Income Statement'!E12,'Income Statement'!F12) -> 0.0050908591 | C10: avg of last 3 yrs
A11: Change in inventory % of sales | B11: =AVERAGE('Income Statement'!D8,'Income Statement'!E8,'Income Statement'!F8) -> -0.098333125 | C11: avg of last 3 yrs
A12: Other Income % of sales | B12: =AVERAGE('Income Statement'!D24,'Income Statement'!E24,'Income Statement'!F24) -> 0.007882247 | C12: avg of last 3 yrs
A13: Interest % of sales | B13: NA | C13: Held flat
A14: Tax Rate | B14: =AVERAGE('Income Statement'!E28,'Income Statement'!F28) -> 0.25912393 | C14: avg Tax/PBT last 2 yrs
A15: Inventory days | B15: =AVERAGE('Balance Sheet'!D22,'Balance Sheet'!E22,'Balance Sheet'!F22) -> 181.90127 | C15: avg of last 3 yrs
A16: Receivable days | B16: =AVERAGE('Balance Sheet'!D24,'Balance Sheet'!E24,'Balance Sheet'!F24) -> 5.8463551 | C16: avg of last 3 yrs
A17: Payable days | B17: =AVERAGE('Balance Sheet'!D12,'Balance Sheet'!E12,'Balance Sheet'!F12) -> 12.738111 | C17: avg of last 3 yrs
A18: Capex % of sales | B18: =AVERAGE('Income Statement'!D30,'Income Statement'!E30,'Income Statement'!F30) -> -0.010665552 | C18: avg of last 3 yrs
A19: Dividend payout ratio | B19: =AVERAGE('Income Statement'!D29,'Income Statement'!E29,'Income Statement'!F29) -> -0.24629131 | C19: avg of last 3 yrs
A20: Risk free rate | B20: 0.068 | C20: current India 10-year G-Sec yield
A21: Beta | B21: 0.99 | C21: eta per TradingView/TipRanks
A22: Equit risk premium | B22: 0.06 | C22: Standard estimate for India
A23: Cost of Debt | B23: ='Income Statement'!K21/'Balance Sheet'!K10 -> 0.038535645
A24: Market Value of Equity | B24: 449575
A25: Market Value of Debt | B25: ='Balance Sheet'!K10 -> 30621
A26: Current share price | B26: 5064
A27: NOS | B27: =B24/B26 -> 88.778633
A28: Cost of Equity (CAPM) | B28: =B20+(B21*B22) -> 0.1274
A29: WACC | B29: =((B24/(B24+B25))*B28)+(B25/(B24+B25)*B23*(1-B14)) -> 0.12109657
A30: Terminal growth rate | B30: 0.045
A32: Note: | B32: At 12% growth, model generates positive and growing cash every forecast year — contrast with 17% scenario, which showed cash turning negative by FY30 due to working-capital intensity outpacing cash generation.

Sheet Income Statement
B1: Actual | G1: Forecast
B2: FY 2022 | C2: FY 2023 | D2: FY 2024 | E2: FY 2025 | F2: FY 2026 | G2: FY 2027 | H2: FY 2028 | I2: FY 2029 | J2: FY 2030 | K2: FY 2031
A3: Sales | B3: 28799 | C3: 40575 | D3: 51084 | E3: 60456 | F3: 87584 | G3: =F3*(1+Assumptions!$B$3) -> 98094.08 | H3: =G3*(1+Assumptions!$B$3) -> 109865.37 | I3: =H3*(1+Assumptions!$B$3) -> 123049.21 | J3: =I3*(1+Assumptions!$B$3) -> 137815.12 | K3: =J3*(1+Assumptions!$B$3) -> 154352.93
C4: =(C3-B3)/B3 -> 0.40890309 | D4: =(D3-C3)/C3 -> 0.25900185 | E4: =(E3-D3)/D3 -> 0.18346253 | F4: =(F3-E3)/E3 -> 0.44872304
A5: Raw Material Cost | B5: 26436 | C5: 32589 | D5: 42103 | E5: 55271 | F5: 80243 | G5: =G3*Assumptions!$B$4 -> 86800.508 | H5: =H3*Assumptions!$B$4 -> 97216.569 | I5: =I3*Assumptions!$B$4 -> 108882.56 | J5: =J3*Assumptions!$B$4 -> 121948.46 | K5: =K3*Assumptions!$B$4 -> 136582.28
B6: =B5/B3 -> 0.91794854 | C6: =C5/C3 -> 0.8031793 | D6: =D5/D3 -> 0.82419153 | E6: =E5/E3 -> 0.91423515 | F6: =F5/F3 -> 0.91618332
A7: Change in Inventory | B7: -4795 | C7: -2234 | D7: -2671 | E7: -7815 | F7: -9936 | G7: =G3*Assumptions!$B$11 -> -9645.8974 | H7: =H3*Assumptions!$B$11 -> -10803.405 | I7: =I3*Assumptions!$B$11 -> -12099.814 | J7: =J3*Assumptions!$B$11 -> -13551.791 | K7: =K3*Assumptions!$B$11 -> -15178.006
B8: =B7/B3 -> -0.16649884 | C8: =C7/C3 -> -0.055058534 | D8: =D7/D3 -> -0.05228643 | E8: =E7/E3 -> -0.12926757 | F8: =F7/F3 -> -0.11344538
A9: Power and Fuel | B9: 45 | C9: 59 | D9: 71 | E9: 78 | F9: 87 | G9: =G3*Assumptions!$B$9 -> 120.11274 | H9: =H3*Assumptions!$B$9 -> 134.52627 | I9: =I3*Assumptions!$B$9 -> 150.66943 | J9: =J3*Assumptions!$B$9 -> 168.74976 | K9: =K3*Assumptions!$B$9 -> 188.99973
B10: =B9/B3 -> 0.0015625543 | C10: =C9/C3 -> 0.0014540974 | D10: =D9/D3 -> 0.0013898677 | E10: =E9/E3 -> 0.0012901945 | F10: =F9/F3 -> 0.00099333212
A11: Other Mfr. Exp | B11: 183 | C11: 225 | D11: 286 | E11: 326 | F11: 375 | G11: =G3*Assumptions!$B$10 -> 499.38314 | H11: =H3*Assumptions!$B$10 -> 559.30912 | I11: =I3*Assumptions!$B$10 -> 626.42621 | J11: =J3*Assumptions!$B$10 -> 701.59736 | K11: =K3*Assumptions!$B$10 -> 785.78904
B12: =B11/B3 -> 0.0063543873 | C12: =C11/C3 -> 0.0055452865 | D12: =D11/D3 -> 0.0055986219 | E12: =E11/E3 -> 0.0053923515 | F12: =F11/F3 -> 0.0042816039
A13: Employee Cost | B13: 1356 | C13: 1656 | D13: 1875 | E13: 2164 | F13: 2692 | G13: =G3*Assumptions!$B$5 -> 3375.5836 | H13: =H3*Assumptions!$B$5 -> 3780.6537 | I13: =I3*Assumptions!$B$5 -> 4234.3321 | J13: =J3*Assumptions!$B$5 -> 4742.4519 | K13: =K3*Assumptions!$B$5 -> 5311.5462
B14: =B13/B3 -> 0.047084968 | C14: =C13/C3 -> 0.040813309 | D14: =D13/D3 -> 0.036704252 | E14: =E13/E3 -> 0.035794627 | F14: =F13/F3 -> 0.030736208
A15: Selling and admin | B15: 1697 | C15: 2715 | D15: 3249 | E15: 3494 | F15: 4185 | G15: =G3*Assumptions!$B$6 -> 5531.7843 | H15: =H3*Assumptions!$B$6 -> 6195.5984 | I15: =I3*Assumptions!$B$6 -> 6939.0703 | J15: =J3*Assumptions!$B$6 -> 7771.7587 | K15: =K3*Assumptions!$B$6 -> 8704.3697
B16: =B15/B3 -> 0.058925657 | C16: =C15/C3 -> 0.066913124 | D16: =D15/D3 -> 0.063601128 | E16: =E15/E3 -> 0.057794098 | F16: =F15/F3 -> 0.0477827
A17: Other Expenses | B17: 533 | C17: 683 | D17: 879 | E17: 1244 | F17: 1581 | G17: =G3*Assumptions!$B$7 -> 1825.699 | H17: =H3*Assumptions!$B$7 -> 2044.7829 | I17: =I3*Assumptions!$B$7 -> 2290.1569 | J17: =J3*Assumptions!$B$7 -> 2564.9757 | K17: =K3*Assumptions!$B$7 -> 2872.7728
B18: =B17/B3 -> 0.018507587 | C18: =C17/C3 -> 0.016833025 | D18: =D17/D3 -> 0.017206953 | E18: =E17/E3 -> 0.020576949 | F18: =F17/F3 -> 0.018051242
A19: Depreciation | B19: 399 | C19: 441 | D19: 584 | E19: 693 | F19: 826 | G19: =G3*Assumptions!$B$8 -> 1056.9957 | H19: =H3*Assumptions!$B$8 -> 1183.8352 | I19: =I3*Assumptions!$B$8 -> 1325.8954 | J19: =J3*Assumptions!$B$8 -> 1485.0029 | K19: =K3*Assumptions!$B$8 -> 1663.2033
B20: =B19/B3 -> 0.013854648 | C20: =C19/C3 -> 0.010868762 | D20: =D19/D3 -> 0.011432151 | E20: =E19/E3 -> 0.011462882 | F20: =F19/F3 -> 0.0094309463
A21: Interest | B21: 218 | C21: 300 | D21: 619 | E21: 953 | F21: 1180 | G21: 1180 | H21: 1180 | I21: 1180 | J21: 1180 | K21: 1180
A22: Total Expense | B22: =B5+B7+B9+B11+B13+B15+B17+B19+B21 -> 26072 | C22: =C5+C7+C9+C11+C13+C15+C17+C19+C21 -> 36434 | D22: =D5+D7+D9+D11+D13+D15+D17+D19+D21 -> 46995 | E22: =E5+E7+E9+E11+E13+E15+E17+E19+E21 -> 56408 | F22: =F5+F7+F9+F11+F13+F15+F17+F19+F21 -> 81233 | G22: =G5+G7+G9+G11+G13+G15+G17+G19+G21 -> 90744.17 | H22: =H5+H7+H9+H11+H13+H15+H17+H19+H21 -> 101491.87 | I22: =I5+I7+I9+I11+I13+I15+I17+I19+I21 -> 113529.29 | ... K22: =K5+K7+K9+K11+K13+K15+K17+K19+K21 -> 142110.95
A23: Other Income | B23: 177 | C23: 306 | D23: 534 | E23: 487 | F23: 450 | G23: =G3*Assumptions!$B$12 -> 773.20177 | H23: =H3*Assumptions!$B$12 -> 865.98598 | I23: =I3*Assumptions!$B$12 -> 969.90429 | J23: =J3*Assumptions!$B$12 -> 1086.2928 | K23: =K3*Assumptions!$B$12 -> 1216.6479
B24: =B23/B3 -> 0.0061460467 | C24: =C23/C3 -> 0.0075415896 | D24: =D23/D3 -> 0.010453371 | E24: =E23/E3 -> 0.0080554453 | F24: =F23/F3 -> 0.0051379247
A25: Profit before tax | B25: =B3+B23-B22 -> 2904 | C25: =C3+C23-C22 -> 4447 | D25: =D3+D23-D22 -> 4623 | E25: =E3+E23-E22 -> 4535 | F25: =F3+F23-F22 -> 6801 | G25: =G3+G23-G22 -> 8123.1122 | H25: =H3+H23-H22 -> 9239.4856 | I25: =I3+I23-I22 -> 10489.824 | ... K25: =K3+K23-K22 -> 13458.627
A26: Tax | B26: 706 | C26: 1173 | D26: 1127 | E26: 1198 | F26: 1728 | G26: =G25*Assumptions!$B$14 -> 2104.8928 | H26: =H25*Assumptions!$B$14 -> 2394.1719 | I26: =I25*Assumptions!$B$14 -> 2718.1644 | J26: =J25*Assumptions!$B$14 -> 3081.0361 | K26: =K25*Assumptions!$B$14 -> 3487.4524
A27: Net profit | B27: =B25-B26 -> 2198 | C27: =C25-C26 -> 3274 | D27: =D25-D26 -> 3496 | E27: =E25-E26 -> 3337 | F27: =F25-F26 -> 5073 | G27: =G25-G26 -> 6018.2194 | H27: =H25-H26 -> 6845.3138 | I27: =I25-I26 -> 7771.6595 | ... K27: =K25-K26 -> 9971.1747
A28: Tax rate | B28: =B26/B25 -> 0.24311295 | C28: =C26/C25 -> 0.26377333 | D28: =D26/D25 -> 0.24378109 | E28: =E26/E25 -> 0.26416759 | F28: =F26/F25 -> 0.25408028
A29: Dividend payout | B29: ='Cash Flow'!B10/'Income Statement'!B27 -> -0.16151046 | C29: ='Cash Flow'!C10/'Income Statement'!C27 -> -0.20342089 | D29: ='Cash Flow'!D10/'Income Statement'!D27 -> -0.25400458 | E29: ='Cash Flow'!E10/'Income Statement'!E27 -> -0.29247827 | F29: ='Cash Flow'!F10/'Income Statement'!F27 -> -0.19239109
A30: Fixed assets | B30: ='Cash Flow'!B5/'Income Statement'!B3 -> -0.0077780478 | C30: ='Cash Flow'!C5/'Income Statement'!C3 -> -0.01064695 | D30: ='Cash Flow'!D5/'Income Statement'!D3 -> -0.01352674 | E30: ='Cash Flow'!E5/'Income Statement'!E3 -> -0.008171232 | F30: ='Cash Flow'!F5/'Income Statement'!F3 -> -0.010298685

Sheet Balance Sheet
B1: Actual | G1: Forecast
B2: FY 2022 | C2: FY 2023 | D2: FY 2024 | E2: FY 2025 | F2: FY 2026 | G2: FY 2027 | H2: FY 2028 | I2: FY 2029 | J2: FY 2030 | K2: FY 2031
A3: Equity Share Capital | B3: 89 | C3: 89 | D3: 89 | E3: 89 | F3: 89 | G3: 89 | H3: 89 | I3: 89 | J3: 89 | K3: 89
A4: Reserves | B4: 9214 | C4: 11762 | D4: 9304 | E4: 11535 | F4: 15614 | G4: =F4+'Income Statement'!G27+'Cash Flow'!G10 -> 20149.984 | H4: =G4+'Income Statement'!H27+'Cash Flow'!H10 -> 25309.357 | I4: =H4+'Income Statement'!I27+'Cash Flow'!I10 -> 31166.924 | J4: =I4+'Income Statement'!J27+'Cash Flow'!J10 -> 37806.469 | K4: =J4+'Income Statement'!K27+'Cash Flow'!K10 -> 45321.83
A5: Non controlling int | B5: 30 | C5: 53 | D5: 0 | E5: 0 | F5: 0 | G5: 0 | H5: 0 | I5: 0 | J5: 0 | K5: 0
A6: Total Equity | B6: =SUM(B3:B5) -> 9333 | C6: =SUM(C3:C5) -> 11904 | D6: =SUM(D3:D5) -> 9393 | E6: =SUM(E3:E5) -> 11624 | F6: =SUM(F3:F5) -> 15703 | G6: =SUM(G3:G5) -> 20238.984 | H6: =SUM(H3:H5) -> 25398.357 | I6: =SUM(I3:I5) -> 31255.924 | ... K6: =SUM(K3:K5) -> 45410.83
A7: Long term Borrowings | B7: 2 | C7: 0 | D7: 3302 | E7: 595 | F7: 93 | G7: 93 | H7: 93 | I7: 93 | J7: 93 | K7: 93
A8: Short term Borrowings | B8: 5914 | C8: 7494 | D8: 9877 | E8: 17501 | F8: 27355 | G8: 27355 | H8: 27355 | I8: 27355 | J8: 27355 | K8: 27355
A9: Lease Liabilities | B9: 1359 | C9: 1873 | D9: 2349 | E9: 2681 | F9: 3173 | G9: 3173 | H9: 3173 | I9: 3173 | J9: 3173 | K9: 3173
A10: Total Borrowings | B10: =SUM(B7:B9) -> 7275 | C10: =SUM(C7:C9) -> 9367 | D10: =SUM(D7:D9) -> 15528 | E10: =SUM(E7:E9) -> 20777 | F10: =SUM(F7:F9) -> 30621 | G10: =SUM(G7:G9) -> 30621 | H10: =SUM(H7:H9) -> 30621 | I10: =SUM(I7:I9) -> 30621 | ... K10: =SUM(K7:K9) -> 30621
A11: Trade Payables | B11: 1294 | C11: 1214 | D11: 1410 | E11: 1963 | F11: 2864 | G11: =Assumptions!$B$17/365*'Income Statement'!G5 -> 3029.2451 | H11: =Assumptions!$B$17/365*'Income Statement'!H5 -> 3392.7546 | I11: =Assumptions!$B$17/365*'Income Statement'!I5 -> 3799.8851 | J11: =Assumptions!$B$17/365*'Income Statement'!J5 -> 4255.8713 | K11: =Assumptions!$B$17/365*'Income Statement'!K5 -> 4766.5759
B12: =(B11/'Income Statement'!B5)*365 -> 17.866167 | C12: =(C11/'Income Statement'!C5)*365 -> 13.596919 | D12: =(D11/'Income Statement'!D5)*365 -> 12.223595 | E12: =(E11/'Income Statement'!E5)*365 -> 12.963308 | F12: =(F11/'Income Statement'!F5)*365 -> 13.027429
A13: Advance from Customers | B13: 532 | C13: 718 | D13: 1085 | E13: 2140 | F13: 4745 | G13: 4745 | H13: 4745 | I13: 4745 | J13: 4745 | K13: 4745
A14: Other liability items | B14: 2754 | C14: 3817 | D14: 4131 | E14: 4141 | F14: 6628 | G14: 6628 | H14: 6628 | I14: 6628 | J14: 6628 | K14: 6628
A15: Total Other liabilities | B15: =SUM(B11:B14)-B12 -> 4580 | C15: =SUM(C11:C14)-C12 -> 5749 | D15: =SUM(D11:D14)-D12 -> 6626 | E15: =SUM(E11:E14)-E12 -> 8244 | F15: =SUM(F11:F14)-F12 -> 14237 | G15: =SUM(G11:G14)-G12 -> 14402.245 | H15: =SUM(H11:H14)-H12 -> 14765.755 | I15: =SUM(I11:I14)-I12 -> 15172.885 | ... K15: =SUM(K11:K14)-K12 -> 16139.576
A16: Total | B16: =B15+B10+B6 -> 21188 | C16: =C15+C10+C6 -> 27020 | D16: =D15+D10+D6 -> 31547 | E16: =E15+E10+E6 -> 40645 | F16: =F15+F10+F6 -> 60561 | G16: =G15+G10+G6 -> 65262.229 | H16: =H15+H10+H6 -> 70785.111 | I16: =I15+I10+I6 -> 77049.809 | ... K16: =K15+K10+K6 -> 92171.406
A18: Fixed Assets | B18: 2544 | C18: 2998 | D18: 3709 | E18: 4062 | F18: 6878 | G18: =F18-'Cash Flow'!G5-'Income Statement'!G19 -> 6867.2318 | H18: =G18-'Cash Flow'!H5-'Income Statement'!H19 -> 6855.1714 | I18: =H18-'Cash Flow'!I5-'Income Statement'!I19 -> 6841.6638 | J18: =I18-'Cash Flow'!J5-'Income Statement'!J19 -> 6826.5353 | K18: =J18-'Cash Flow'!K5-'Income Statement'!K19 -> 6809.5913
A19: Capital Work in Progress | B19: 85 | C19: 144 | D19: 97 | E19: 105 | F19: 163 | G19: 163 | H19: 163 | I19: 163 | J19: 163 | K19: 163
A20: Investments | B20: 294 | C20: 2515 | D20: 2345 | E20: 1988 | F20: 3506 | G20: 3506 | H20: 3506 | I20: 3506 | J20: 3506 | K20: 3506
A21: Inventories | B21: 13609 | C21: 16584 | D21: 19051 | E21: 28184 | F21: 42743 | G21: =Assumptions!$B$15/365*'Income Statement'!G5 -> 43257.87 | H21: =Assumptions!$B$15/365*'Income Statement'!H5 -> 48448.814 | I21: =Assumptions!$B$15/365*'Income Statement'!I5 -> 54262.672 | J21: =Assumptions!$B$15/365*'Income Statement'!J5 -> 60774.193 | K21: =Assumptions!$B$15/365*'Income Statement'!K5 -> 68067.096
B22: =(B21/'Income Statement'!B5)*365 -> 187.89851 | C22: =(C21/'Income Statement'!C5)*365 -> 185.74243 | D22: =(D21/'Income Statement'!D5)*365 -> 165.15723 | E22: =(E21/'Income Statement'!E5)*365 -> 186.1222 | F22: =(F21/'Income Statement'!F5)*365 -> 194.42437
A23: Trade receivables | B23: 565 | C23: 674 | D23: 1018 | E23: 1068 | F23: 916 | G23: =Assumptions!$B$16/365*'Income Statement'!G3 -> 1571.2132 | H23: =Assumptions!$B$16/365*'Income Statement'!H3 -> 1759.7588 | I23: =Assumptions!$B$16/365*'Income Statement'!I3 -> 1970.9298 | J23: =Assumptions!$B$16/365*'Income Statement'!J3 -> 2207.4414 | K23: =Assumptions!$B$16/365*'Income Statement'!K3 -> 2472.3344
B24: =(B23/'Income Statement'!B3)*365 -> 7.1608389 | C24: =(C23/'Income Statement'!C3)*365 -> 6.063093 | D24: =(D23/'Income Statement'!D3)*365 -> 7.2737061 | E24: =(E23/'Income Statement'!E3)*365 -> 6.4479952 | F24: =(F23/'Income Statement'!F3)*365 -> 3.8173639
A25: Cash Equivalents | B25: 1573 | C25: 1343 | D25: 1526 | E25: 1584 | F25: 1917 | G25: =F25+'Cash Flow'!G12 -> 5458.9143 | H25: =G25+'Cash Flow'!H12 -> 5614.3666 | I25: =H25+'Cash Flow'!I12 -> 5867.5432 | J25: =I25+'Cash Flow'!J12 -> 6230.1712 | K25: =J25+'Cash Flow'!K12 -> 6715.3846
A26: Loans n Advances | B26: 29 | C26: 167 | D26: 151 | E26: 324 | F26: 399 | G26: 399 | H26: 399 | I26: 399 | J26: 399 | K26: 399
A27: Other asset items | B27: 2489 | C27: 2595 | D27: 3650 | E27: 3330 | F27: 4039 | G27: 4039 | H27: 4039 | I27: 4039 | J27: 4039 | K27: 4039
A28: Total Other Assets | B28: =SUM(B21:B27)-B22-B24 -> 18265 | C28: =SUM(C21:C27)-C22-C24 -> 21363 | D28: =SUM(D21:D27)-D22-D24 -> 25396 | E28: =SUM(E21:E27)-E22-E24 -> 34490 | F28: =SUM(F21:F27)-F22-F24 -> 50014 | G28: =SUM(G21:G27)-G22-G24 -> 54725.998 | H28: =SUM(H21:H27)-H22-H24 -> 60260.94 | I28: =SUM(I21:I27)-I22-I24 -> 66539.145 | ... K28: =SUM(K21:K27)-K22-K24 -> 81692.815
A29: Total | B29: =SUM(B18:B20)+B28 -> 21188 | C29: =SUM(C18:C20)+C28 -> 27020 | D29: =SUM(D18:D20)+D28 -> 31547 | E29: =SUM(E18:E20)+E28 -> 40645 | F29: =SUM(F18:F20)+F28 -> 60561 | G29: =SUM(G18:G20)+G28 -> 65262.229 | H29: =SUM(H18:H20)+H28 -> 70785.111 | I29: =SUM(I18:I20)+I28 -> 77049.809 | ... K29: =SUM(K18:K20)+K28 -> 92171.406

Sheet Cash Flow
B1: Actual | G1: Forecast
B2: FY 2022 | C2: FY 2023 | D2: FY 2024 | E2: FY 2025 | F2: FY 2026 | G2: FY 2027 | H2: FY 2028 | I2: FY 2029 | J2: FY 2030 | K2: FY 2031
A3: Cash from Operating Activity | B3: -724 | C3: 1370 | D3: 1695 | E3: -541 | F3: 5590 | G3: ='Income Statement'!G27+'Income Statement'!G19-('Balance Sheet'!G21-'Balance Sheet'!F21)-('Balance Sheet'!G23-'Balance Sheet'!F23)+('Balance Sheet'!G11-'Balance Sheet'!F11)+'Income Statement'!G21 -> 7250.377 | H3: ='Income Statement'!H27+'Income Statement'!H19-('Balance Sheet'!H21-'Balance Sheet'!G21)-('Balance Sheet'!H23-'Balance Sheet'!G23)+('Balance Sheet'!H11-'Balance Sheet'!G11)+'Income Statement'!H21 -> 4193.1684 | I3: ='Income Statement'!I27+'Income Statement'!I19-('Balance Sheet'!I21-'Balance Sheet'!H21)-('Balance Sheet'!I23-'Balance Sheet'!H23)+('Balance Sheet'!I11-'Balance Sheet'!H11)+'Income Statement'!I21 -> 4659.6567 | J3: ='Income Statement'!J27+'Income Statement'!J19-('Balance Sheet'!J21-'Balance Sheet'!I21)-('Balance Sheet'!J23-'Balance Sheet'!I23)+('Balance Sheet'!J11-'Balance Sheet'!I11)+'Income Statement'!J21 -> 5182.1235 | K3: ='Income Statement'!K27+'Income Statement'!K19-('Balance Sheet'!K21-'Balance Sheet'!J21)-('Balance Sheet'!K23-'Balance Sheet'!J23)+('Balance Sheet'!K11-'Balance Sheet'!J11)+'Income Statement'!K21 -> 5767.2864
A4: Cash from Investing Activity | B4: =SUM(B5:B6) -> 1165 | C4: =SUM(C5:C6) -> -1814 | D4: =SUM(D5:D6) -> -189 | E4: =SUM(E5:E6) -> 546 | F4: =SUM(F5:F6) -> -2965 | G4: =SUM(G5:G6) -> -1046.2275 | H4: =SUM(H5:H6) -> -1171.7748 | I4: =SUM(I5:I6) -> -1312.3878 | ... K4: =SUM(K5:K6) -> -1646.2593
A5: _ Fixed asset purchased | B5: -224 | C5: -432 | D5: -691 | E5: -494 | F5: -902 | G5: ='Income Statement'!G3*Assumptions!$B$18 -> -1046.2275 | H5: ='Income Statement'!H3*Assumptions!$B$18 -> -1171.7748 | I5: ='Income Statement'!I3*Assumptions!$B$18 -> -1312.3878 | J5: ='Income Statement'!J3*Assumptions!$B$18 -> -1469.8744 | K5: ='Income Statement'!K3*Assumptions!$B$18 -> -1646.2593
A6: _Other investing activity | B6: 1389 | C6: -1382 | D6: 502 | E6: 1040 | F6: -2063 | G6: 0 | H6: 0 | I6: 0 | J6: 0 | K6: 0
A7: Cash from Financing Activity | B7: =SUM(B8:B11) -> -403 | C7: =SUM(C8:C11) -> 457 | D7: =SUM(D8:D11) -> -1329 | E7: =SUM(E8:E11) -> -7 | F7: =SUM(F8:F11) -> -2159 | G7: =SUM(G8:G11) -> -2662.2352 | H7: =SUM(H8:H11) -> -2865.9413 | I7: =SUM(I8:I11) -> -3094.0922 | ... K7: =SUM(K8:K11) -> -3635.8137
A8: _Net proceeds from borrowings | B8: 342 | C8: 1677 | D8: 5629 | E8: 2221 | F8: 682 | G8: 0 | H8: 0 | I8: 0 | J8: 0 | K8: 0
A9: _Interest paid | B9: -218 | C9: -300 | D9: -619 | E9: -538 | F9: -1000 | G9: =-'Income Statement'!G21 -> -1180 | H9: =-'Income Statement'!H21 -> -1180 | I9: =-'Income Statement'!I21 -> -1180 | J9: =-'Income Statement'!J21 -> -1180 | K9: =-'Income Statement'!K21 -> -1180
A10: _Dividends paid | B10: -355 | C10: -666 | D10: -888 | E10: -976 | F10: -976 | G10: ='Income Statement'!G27*Assumptions!$B$19 -> -1482.2352 | H10: ='Income Statement'!H27*Assumptions!$B$19 -> -1685.9413 | I10: ='Income Statement'!I27*Assumptions!$B$19 -> -1914.0922 | J10: ='Income Statement'!J27*Assumptions!$B$19 -> -2169.6212 | K10: ='Income Statement'!K27*Assumptions!$B$19 -> -2455.8137
A11: _Other financing activity | B11: -172 | C11: -254 | D11: -5451 | E11: -714 | F11: -865 | G11: 0 | H11: 0 | I11: 0 | J11: 0 | K11: 0
A12: Net Cash Flow | B12: =B7+B4+B3 -> 38 | C12: =C7+C4+C3 -> 13 | D12: =D7+D4+D3 -> 177 | E12: =E7+E4+E3 -> -2 | F12: =F7+F4+F3 -> 466 | G12: =G7+G4+G3 -> 3541.9143 | H12: =H7+H4+H3 -> 155.45226 | I12: =I7+I4+I3 -> 253.17664 | ... K12: =K7+K4+K3 -> 485.21341

Sheet DCF
G1: Forecast
G2: FY 2027 | H2: FY 2028 | I2: FY 2029 | J2: FY 2030 | K2: FY 2031
A3: EBIT | G3: ='Income Statement'!G25+'Income Statement'!G21 -> 9303.1122 | H3: ='Income Statement'!H25+'Income Statement'!H21 -> 10419.486 | I3: ='Income Statement'!I25+'Income Statement'!I21 -> 11669.824 | J3: ='Income Statement'!J25+'Income Statement'!J21 -> 13070.203 | K3: ='Income Statement'!K25+'Income Statement'!K21 -> 14638.627
A4: Less: Tax on EBIT | G4: =-G3*Assumptions!$B$14 -> -2410.659 | H4: =-H3*Assumptions!$B$14 -> -2699.9381 | I4: =-I3*Assumptions!$B$14 -> -3023.9307 | J4: =-J3*Assumptions!$B$14 -> -3386.8024 | K4: =-K3*Assumptions!$B$14 -> -3793.2186
A5: NOPAT | G5: =SUM(G3:G4) -> 6892.4532 | H5: =SUM(H3:H4) -> 7719.5475 | I5: =SUM(I3:I4) -> 8645.8932 | J5: =SUM(J3:J4) -> 9683.4004 | K5: =SUM(K3:K4) -> 10845.408
A6: Add: Depreciation | G6: ='Income Statement'!G19 -> 1056.9957 | H6: ='Income Statement'!H19 -> 1183.8352 | I6: ='Income Statement'!I19 -> 1325.8954 | J6: ='Income Statement'!J19 -> 1485.0029 | K6: ='Income Statement'!K19 -> 1663.2033
A7: Less: Capex | G7: ='Cash Flow'!G5 -> -1046.2275 | H7: ='Cash Flow'!H5 -> -1171.7748 | I7: ='Cash Flow'!I5 -> -1312.3878 | J7: ='Cash Flow'!J5 -> -1469.8744 | K7: ='Cash Flow'!K5 -> -1646.2593
A8: Less: Increase in Net Working Capital | G8: =-(('Balance Sheet'!G21+'Balance Sheet'!G23-'Balance Sheet'!G11)-('Balance Sheet'!F21+'Balance Sheet'!F23-'Balance Sheet'!F11)) -> -1004.8381 | H8: =-(('Balance Sheet'!H21+'Balance Sheet'!H23-'Balance Sheet'!H11)-('Balance Sheet'!G21+'Balance Sheet'!G23-'Balance Sheet'!G11)) -> -5015.9806 | I8: =-(('Balance Sheet'!I21+'Balance Sheet'!I23-'Balance Sheet'!I11)-('Balance Sheet'!H21+'Balance Sheet'!H23-'Balance Sheet'!H11)) -> -5617.8982 | J8: =-(('Balance Sheet'!J21+'Balance Sheet'!J23-'Balance Sheet'!J11)-('Balance Sheet'!I21+'Balance Sheet'!I23-'Balance Sheet'!I11)) -> -6292.046 | K8: =-(('Balance Sheet'!K21+'Balance Sheet'!K23-'Balance Sheet'!K11)-('Balance Sheet'!J21+'Balance Sheet'!J23-'Balance Sheet'!J11)) -> -7047.0916
A9: FCFF | G9: =SUM(G5:G8) -> 5898.3832 | H9: =SUM(H5:H8) -> 2715.6273 | I9: =SUM(I5:I8) -> 3041.5026 | J9: =SUM(J5:J8) -> 3406.4829 | K9: =SUM(K5:K8) -> 3815.2609
A11: Terminal Value | K11: =K9*(1+Assumptions!B30)/(Assumptions!B29-Assumptions!B30) -> 52393.263
A13: Discount Factor | G13: =1/(1+Assumptions!$B$29)^1 -> 0.89198382 | H13: =1/(1+Assumptions!$B$29)^2 -> 0.79563513 | I13: =1/(1+Assumptions!$B$29)^3 -> 0.70969366 | J13: =1/(1+Assumptions!$B$29)^4 -> 0.63303526 | K13: =1/(1+Assumptions!$B$29)^5 -> 0.56465721
A15: PV of FCFF | G15: =G9*G13 -> 5261.2624 | H15: =H9*H13 -> 2160.6485 | I15: =I9*I13 -> 2158.5351 | J15: =J9*J13 -> 2156.4238 | K15: =K9*K13 -> 2154.3146
A16: PV of Terminal Value | K16: =K13*K11 -> 29584.234
A18: Enterprise Value | G18: =SUM(G15:K15)+K16 -> 43475.418
A20: Equity Value | G20: =G18-(Assumptions!B25-'Balance Sheet'!F25) -> 14771.418
A22: Implied share price | G22: =G20/Assumptions!B27 -> 166.38483
